graph_model_parser/__init__.py
graph_model_parser/graph_model_parser.py
tests/__init__.py
tests/test_graph_model_parser.py
graph_model_parser-0.1.4.dist-info/METADATA
graph_model_parser-0.1.4.dist-info/WHEEL
graph_model_parser-0.1.4.dist-info/top_level.txt
graph_model_parser-0.1.4.dist-info/RECORD
