Metadata-Version: 2.1
Name: graph-model-parser
Version: 0.1.4
Summary: A Python library for parsing and simulating dynamical graph models from string descriptions
Home-page: https://github.com/albertbuchard/GraphModelParser
Author: Albert Buchard
Classifier: Development Status :: 3 - Alpha
Classifier: Intended Audience :: Developers
Classifier: License :: OSI Approved :: MIT License
Classifier: Programming Language :: Python :: 3
Classifier: Programming Language :: Python :: 3.6
Classifier: Programming Language :: Python :: 3.7
Classifier: Programming Language :: Python :: 3.8
Classifier: Programming Language :: Python :: 3.9
Requires-Dist: numpy
Requires-Dist: scipy
